pykoop/__init__.py
pykoop/centers.py
pykoop/dynamic_models.py
pykoop/kernel_approximation.py
pykoop/koopman_pipeline.py
pykoop/lifting_functions.py
pykoop/lmi_regressors.py
pykoop/regressors.py
pykoop/tsvd.py
pykoop/util.py
pykoop/_sklearn_config/__init__.py
pykoop/_sklearn_config/config.py
pykoop/_sklearn_metaestimators/__init__.py
pykoop/_sklearn_metaestimators/metaestimators.py
pykoop-2.0.1.dist-info/LICENSE
pykoop-2.0.1.dist-info/METADATA
pykoop-2.0.1.dist-info/WHEEL
pykoop-2.0.1.dist-info/top_level.txt
pykoop-2.0.1.dist-info/RECORD
