Metadata-Version: 2.1
Name: pykoop
Version: 2.0.1
Summary: Koopman operator identification library in Python, compatible with `scikit-learn`
Home-page: https://github.com/decargroup/pykoop
Author: Steven Dahdah
Author-email: steven.dahdah@mail.mcgill.ca
Project-URL: Documentation, https://pykoop.readthedocs.io/en/stable
Project-URL: Source, https://github.com/decargroup/pykoop
Project-URL: Tracker, https://github.com/decargroup/pykoop/issues
Project-URL: PyPI, https://pypi.org/project/pykoop/
Project-URL: DOI, https://doi.org/10.5281/zenodo.5576490
Classifier: Programming Language :: Python :: 3
Classifier: License :: OSI Approved :: MIT License
Classifier: Operating System :: OS Independent
Classifier: Topic :: Scientific/Engineering
Requires-Python: >=3.7
License-File: LICENSE
Requires-Dist: numpy >=1.21.0
Requires-Dist: scipy >=1.7.0
Requires-Dist: scikit-learn >=1.0.0
Requires-Dist: picos >=2.4.0
Requires-Dist: optht >=0.2.0
Requires-Dist: Deprecated >=1.2.13
Requires-Dist: matplotlib >=3.5.1
